meshcat/__init__.py
meshcat/animation.py
meshcat/commands.py
meshcat/geometry.py
meshcat/path.py
meshcat/transformations.py
meshcat/visualizer.py
meshcat/servers/__init__.py
meshcat/servers/tree.py
meshcat/servers/zmqserver.py
meshcat/viewer/.git
meshcat/viewer/.gitmodules
meshcat/viewer/LICENSE
meshcat/viewer/package.json
meshcat/viewer/webpack.config.js
meshcat/viewer/dist/index.html
meshcat/viewer/dist/main.min.js
meshcat/viewer/dist/main.min.js.THIRD_PARTY_LICENSES.json
meshcat/viewer/src/index.js
meshcat_sim_web_fork-0.4.0.dist-info/LICENSE.txt
meshcat_sim_web_fork-0.4.0.dist-info/METADATA
meshcat_sim_web_fork-0.4.0.dist-info/WHEEL
meshcat_sim_web_fork-0.4.0.dist-info/entry_points.txt
meshcat_sim_web_fork-0.4.0.dist-info/top_level.txt
meshcat_sim_web_fork-0.4.0.dist-info/RECORD
