Metadata-Version: 2.1
Name: meshcat-sim-web-fork
Version: 0.4.0
Summary: WebGL-based visualizer for 3D geometries and scenes
Home-page: https://github.com/rdeits/meshcat-python
Author: Robin Deits
Author-email: mail@robindeits.com
License: MIT
License-File: LICENSE.txt
Requires-Dist: ipython >=5
Requires-Dist: u-msgpack-python >=2.4.1
Requires-Dist: numpy >=1.14.0
Requires-Dist: tornado >=4.0.0
Requires-Dist: pyzmq >=17.0.0
Requires-Dist: pyngrok >=4.1.6
Requires-Dist: pillow >=7.0.0
